{
  "id": "cresselia",
  "dex": 488,
  "name": "Cresselia",
  "types": [
    "PSYCHIC"
  ],
  "baseStats": {
    "hp": 120,
    "atk": 70,
    "def": 110,
    "spa": 75,
    "spd": 120,
    "spe": 85
  },
  "catchRate": 3,
  "expYield": 290,
  "modelId": "cresselia",
  "learnset": {
    "1": [
      "confusion",
      "double_team"
    ],
    "6": [
      "mist"
    ],
    "12": [
      "aurora_beam"
    ],
    "18": [
      "psybeam"
    ],
    "24": [
      "psycho_shift"
    ],
    "30": [
      "slash"
    ],
    "36": [
      "psycho_cut"
    ],
    "42": [
      "moonlight"
    ],
    "48": [
      "safeguard"
    ],
    "54": [
      "psychic"
    ],
    "60": [
      "moonblast"
    ],
    "66": [
      "future_sight"
    ],
    "72": [
      "lunar_dance",
      "lunar_blessing"
    ]
  },
  "evolution": null,
  "evolutions": null,
  "spawn": null,
  "evYield": {
    "hp": 0,
    "atk": 0,
    "def": 0,
    "spa": 0,
    "spd": 3,
    "spe": 0
  },
  "maleRatio": 0,
  "abilities": [
    "levitate"
  ],
  "hiddenAbility": "levitate"
}
