{
  "id": "gossifleur",
  "dex": 829,
  "name": "Gossifleur",
  "types": [
    "GRASS"
  ],
  "baseStats": {
    "hp": 40,
    "atk": 40,
    "def": 60,
    "spa": 40,
    "spd": 60,
    "spe": 10
  },
  "catchRate": 190,
  "expYield": 50,
  "modelId": "gossifleur",
  "learnset": {
    "1": [
      "leafage",
      "sing"
    ],
    "4": [
      "rapid_spin"
    ],
    "8": [
      "sweet_scent"
    ],
    "12": [
      "razor_leaf"
    ],
    "16": [
      "round"
    ],
    "21": [
      "leaf_tornado"
    ],
    "24": [
      "synthesis"
    ],
    "28": [
      "hyper_voice"
    ],
    "32": [
      "aromatherapy"
    ],
    "36": [
      "leaf_storm"
    ]
  },
  "evolution": null,
  "evolutions": [
    {
      "level": 20,
      "to": "eldegoss",
      "item": null
    }
  ],
  "spawn": {
    "biomes": [
      "FOREST",
      "FLOWER_FOREST",
      "BIRCH_FOREST",
      "JUNGLE"
    ],
    "weight": 15,
    "minLevel": 2,
    "maxLevel": 10
  },
  "evYield": {
    "hp": 0,
    "atk": 0,
    "def": 0,
    "spa": 0,
    "spd": 1,
    "spe": 0
  },
  "maleRatio": 0.5,
  "abilities": [
    "cottondown",
    "regenerator"
  ],
  "hiddenAbility": "effectspore"
}
