{
  "id": "incineroar",
  "dex": 727,
  "name": "Incineroar",
  "types": [
    "FIRE",
    "DARK"
  ],
  "baseStats": {
    "hp": 95,
    "atk": 115,
    "def": 90,
    "spa": 80,
    "spd": 90,
    "spe": 60
  },
  "catchRate": 45,
  "expYield": 265,
  "modelId": "incineroar",
  "learnset": {
    "1": [
      "darkest_lariat",
      "bulk_up",
      "throat_chop",
      "scratch",
      "ember",
      "growl",
      "lick",
      "leer",
      "outrage",
      "cross_chop"
    ],
    "9": [
      "roar"
    ],
    "12": [
      "fury_swipes"
    ],
    "15": [
      "bite"
    ],
    "20": [
      "double_kick"
    ],
    "25": [
      "fire_fang"
    ],
    "30": [
      "scary_face"
    ],
    "32": [
      "swagger"
    ],
    "44": [
      "flamethrower"
    ],
    "51": [
      "thrash"
    ],
    "58": [
      "flare_blitz"
    ]
  },
  "evolution": null,
  "evolutions": null,
  "spawn": null,
  "evYield": {
    "hp": 0,
    "atk": 3,
    "def": 0,
    "spa": 0,
    "spd": 0,
    "spe": 0
  },
  "maleRatio": 0.875,
  "abilities": [
    "blaze"
  ],
  "hiddenAbility": "intimidate"
}
