{
  "id": "latias",
  "dex": 380,
  "name": "Latias",
  "types": [
    "DRAGON",
    "PSYCHIC"
  ],
  "baseStats": {
    "hp": 80,
    "atk": 80,
    "def": 90,
    "spa": 110,
    "spd": 130,
    "spe": 110
  },
  "catchRate": 3,
  "expYield": 300,
  "modelId": "latias",
  "learnset": {
    "1": [
      "pound"
    ],
    "4": [
      "leer"
    ],
    "8": [
      "twister"
    ],
    "14": [
      "confusion"
    ],
    "20": [
      "dragon_breath"
    ],
    "32": [
      "psybeam"
    ],
    "40": [
      "dragon_claw"
    ],
    "48": [
      "psychic"
    ],
    "26": [
      "calm_mind"
    ]
  },
  "evolution": null,
  "evolutions": null,
  "spawn": null
}
