{
  "id": "mothim",
  "dex": 414,
  "name": "Mothim",
  "types": [
    "BUG",
    "FLYING"
  ],
  "baseStats": {
    "hp": 70,
    "atk": 94,
    "def": 50,
    "spa": 94,
    "spd": 50,
    "spe": 66
  },
  "catchRate": 45,
  "expYield": 148,
  "modelId": "mothim",
  "learnset": {
    "1": [
      "tackle",
      "protect",
      "bug_bite",
      "quiver_dance"
    ],
    "20": [
      "string_shot"
    ],
    "23": [
      "confusion"
    ],
    "26": [
      "gust"
    ],
    "29": [
      "poison_powder"
    ],
    "32": [
      "psybeam"
    ],
    "35": [
      "camouflage"
    ],
    "38": [
      "struggle_bug"
    ],
    "41": [
      "air_slash"
    ],
    "44": [
      "psychic"
    ],
    "47": [
      "lunge"
    ],
    "50": [
      "bug_buzz"
    ]
  },
  "evolution": null,
  "evolutions": null,
  "spawn": null,
  "evYield": {
    "hp": 0,
    "atk": 1,
    "def": 0,
    "spa": 1,
    "spd": 0,
    "spe": 0
  },
  "maleRatio": 1,
  "abilities": [
    "swarm"
  ],
  "hiddenAbility": "tintedlens"
}
