{
  "id": "nidorina",
  "dex": 30,
  "name": "Nidorina",
  "types": [
    "POISON"
  ],
  "baseStats": {
    "hp": 70,
    "atk": 62,
    "def": 67,
    "spa": 55,
    "spd": 55,
    "spe": 56
  },
  "catchRate": 120,
  "expYield": 102,
  "modelId": "nidorina",
  "learnset": {
    "1": [
      "growl",
      "scratch",
      "tail_whip",
      "poison_sting",
      "poison_fang",
      "captivate"
    ],
    "15": [
      "fury_swipes"
    ],
    "22": [
      "toxic_spikes"
    ],
    "29": [
      "double_kick"
    ],
    "36": [
      "bite"
    ],
    "43": [
      "helping_hand"
    ],
    "50": [
      "toxic"
    ],
    "57": [
      "flatter"
    ],
    "64": [
      "crunch"
    ],
    "71": [
      "earth_power"
    ]
  },
  "evolution": null,
  "evolutions": [
    {
      "level": 0,
      "to": "nidoqueen",
      "item": "moon_stone"
    }
  ],
  "spawn": null
}
