{
  "id": "rapidash",
  "dex": 78,
  "name": "Rapidash",
  "types": [
    "FIRE"
  ],
  "baseStats": {
    "hp": 65,
    "atk": 100,
    "def": 70,
    "spa": 80,
    "spd": 80,
    "spe": 105
  },
  "catchRate": 60,
  "expYield": 225,
  "modelId": "rapidash",
  "learnset": {
    "1": [
      "poison_jab",
      "megahorn",
      "growl",
      "quick_attack",
      "tail_whip",
      "ember",
      "fury_attack",
      "smart_strike",
      "tackle"
    ],
    "15": [
      "flame_charge"
    ],
    "20": [
      "agility"
    ],
    "25": [
      "flame_wheel"
    ],
    "30": [
      "stomp"
    ],
    "35": [
      "fire_spin"
    ],
    "43": [
      "take_down"
    ],
    "49": [
      "inferno"
    ],
    "56": [
      "fire_blast"
    ],
    "63": [
      "flare_blitz"
    ]
  },
  "evolution": null,
  "evolutions": null,
  "spawn": null,
  "evYield": {
    "hp": 0,
    "atk": 0,
    "def": 0,
    "spa": 0,
    "spd": 0,
    "spe": 2
  },
  "maleRatio": 0.5,
  "abilities": [
    "runaway",
    "flashfire"
  ],
  "hiddenAbility": "flamebody"
}
