{
  "id": "sceptile",
  "dex": 254,
  "name": "Sceptile",
  "types": [
    "GRASS"
  ],
  "baseStats": {
    "hp": 70,
    "atk": 85,
    "def": 65,
    "spa": 105,
    "spd": 85,
    "spe": 120
  },
  "catchRate": 45,
  "expYield": 265,
  "modelId": "sceptile",
  "learnset": {
    "1": [
      "pound"
    ],
    "4": [
      "sleep_powder"
    ],
    "8": [
      "vine_whip"
    ],
    "14": [
      "razor_leaf"
    ],
    "20": [
      "seed_bomb"
    ],
    "32": [
      "petal_dance"
    ],
    "40": [
      "solar_beam"
    ],
    "26": [
      "agility"
    ]
  },
  "evolution": null,
  "evolutions": null,
  "spawn": null
}
