{
  "id": "yungoos",
  "dex": 734,
  "name": "Yungoos",
  "types": [
    "NORMAL"
  ],
  "baseStats": {
    "hp": 48,
    "atk": 70,
    "def": 30,
    "spa": 30,
    "spd": 30,
    "spe": 45
  },
  "catchRate": 255,
  "expYield": 51,
  "modelId": "yungoos",
  "learnset": {
    "1": [
      "tackle",
      "pursuit",
      "odor_sleuth"
    ],
    "3": [
      "leer"
    ],
    "7": [
      "payback"
    ],
    "10": [
      "sand_attack"
    ],
    "13": [
      "work_up"
    ],
    "19": [
      "bite"
    ],
    "22": [
      "mud_slap"
    ],
    "25": [
      "super_fang"
    ],
    "28": [
      "take_down"
    ],
    "31": [
      "scary_face"
    ],
    "34": [
      "crunch"
    ],
    "37": [
      "hyper_fang"
    ],
    "40": [
      "thrash"
    ],
    "43": [
      "rest"
    ]
  },
  "evolution": null,
  "evolutions": [
    {
      "level": 20,
      "to": "gumshoos",
      "item": null
    }
  ],
  "spawn": {
    "biomes": [
      "PLAINS",
      "SUNFLOWER_PLAINS",
      "MEADOW",
      "SAVANNA"
    ],
    "weight": 20,
    "minLevel": 2,
    "maxLevel": 10
  }
}
